vsix_to_vscodium/__init__.py
vsix_to_vscodium/cli.py
vsix_to_vscodium-0.5.0.dist-info/entry_points.txt
vsix_to_vscodium-0.5.0.dist-info/LICENSE
vsix_to_vscodium-0.5.0.dist-info/WHEEL
vsix_to_vscodium-0.5.0.dist-info/METADATA
vsix_to_vscodium-0.5.0.dist-info/RECORD
