Metadata-Version: 2.3
Name: vsix-to-vscodium
Version: 0.5.0
Summary: A tool to download and install VS Code extensions in VSCodium-based IDEs.
Author-email: Uche Ozoemena <codewithoz@outlook.com>
Requires-Dist: requests>=2.32.3
Requires-Dist: pytest>=8.3.4 ; extra == "test"
Requires-Dist: pytest-cov>=6.0.0 ; extra == "test"
Project-URL: Home, https://github.com/CodeWithOz/vsix-to-vscodium
Provides-Extra: test
